whatnext/__init__.py
whatnext/guide.txt
whatnext/models.py
whatnext/next.py
whatnext/summary.py
whatnext/whatnext.py
whatnext-1.3.2.dist-info/METADATA
whatnext-1.3.2.dist-info/WHEEL
whatnext-1.3.2.dist-info/entry_points.txt
whatnext-1.3.2.dist-info/licenses/LICENCE
whatnext-1.3.2.dist-info/licenses/LICENSE
whatnext-1.3.2.dist-info/RECORD
