Metadata-Version: 2.4
Name: whatnext
Version: 1.3.2
Summary: A lister of tasks found in Markdown files
Project-URL: Homepage, https://github.com/norm/whatnext
Project-URL: Repository, https://github.com/norm/whatnext
Project-URL: Documentation, https://github.com/norm/whatnext
Author: Mark Norman Francis
License-Expression: MIT
License-File: LICENCE
License-File: LICENSE
Keywords: cli,markdown,tasks,todo
Classifier: Development Status :: 3 - Alpha
Classifier: Programming Language :: Python :: 3.10
Classifier: Programming Language :: Python :: 3.11
Classifier: Programming Language :: Python :: 3.12
Requires-Python: >=3.10
Requires-Dist: termcolor
Requires-Dist: toml
Provides-Extra: test
Requires-Dist: flake8; extra == 'test'
Requires-Dist: pytest; extra == 'test'
